APB/slave.v
module slave (
    input  wire       pclk,     // Clock signal
    input  wire       presetn,  // Active-low reset
    input  wire       psel,     // Select signal from master
    input  wire       penable,  // Enable signal from master
    input  wire       pwrite,   // Write signal: 1 for write, 0 for read
    input  wire [7:0] paddr,    // Address from master
    input  wire [7:0] pwdata,   // Write data from master
    output reg  [7:0] prdata,   // Read data to master
    output reg        pready,   // Ready signal to master
    output reg        pslverr   // Error signal to master
);

  // Internal memory: 256 bytes
  reg [7:0] memory[255:0];

  // Address register
  reg [7:0] addr_reg;

  // Reset and initialization logic
  always @(posedge pclk or negedge presetn) begin
    if (!presetn) begin
      pready   <= 1'b0;
      pslverr  <= 1'b0;
      addr_reg <= 8'b0;
    end else begin
      // Pre-setting default values for each cycle
      pready  <= 1'b0;
      pslverr <= 1'b0;

      if (psel) begin
        // Handle Read Operations
        if (!pwrite && penable) begin
          if (paddr <= 8'd255) begin
            addr_reg <= paddr;
            prdata   <= memory[paddr];  // Read data from memory
            pready   <= 1'b1;  // Indicate successful transfer
          end else begin
            pslverr <= 1'b1;  // Address out of range
            pready  <= 1'b1;
          end
        end

        // Handle Write Operations
        if (pwrite && penable) begin
          if (paddr <= 8'd255) begin
            memory[paddr] <= pwdata;  // Write data to memory
            pready        <= 1'b1;  // Indicate successful transfer
          end else begin
            pslverr <= 1'b1;  // Address out of range
            pready  <= 1'b1;
          end
        end
      end
    end
  end

endmodule

APB/master.v
module master (
    input wire       presetn,          // Active-low reset
    input wire       pclk,             // Clock signal
    input wire       transfer,         // Transfer signal to initiate a transaction
    input wire       read,             // Read enable signal
    input wire       write,            // Write enable signal
    input wire [8:0] apb_write_paddr,  // Write address
    input wire [7:0] apb_write_data,   // Write data
    input wire [8:0] apb_read_paddr,   // Read address
    input wire       pready,           // Slave ready signal
    input wire       pslverr,          // Slave error signal
    input wire [7:0] prdata,           // Data from slave during read

    output reg       psel1,             // Select signal for slave 1
    output reg       psel2,             // Select signal for slave 2
    output reg       penable,           // Enable signal for the current transfer
    output reg       pwrite,            // Write signal (1 = write, 0 = read)
    output reg [8:0] paddr,             // Address signal for slave
    output reg [7:0] pwdata,            // Data to slave during write
    output reg [7:0] apb_read_data_out  // Data output during read
);

  // Internal state encoding
  parameter IDLE = 2'b00;
  parameter SETUP = 2'b01;
  parameter ENABLE = 2'b10;

  reg [1:0] state;  // Current state
  reg [1:0] next_state;  // Next state

  // Registered signals to hold values during ENABLE state
  reg       psel1_reg;
  reg       psel2_reg;
  reg       pwrite_reg;
  reg [8:0] paddr_reg;
  reg [7:0] pwdata_reg;
  reg       read_reg;  // To remember if current operation is read
  reg       transfer_reg;  // Register transfer signal to detect completion

  // Sequential state transition logic
  always @(posedge pclk or negedge presetn) begin
    if (!presetn) begin
      state <= IDLE;
      // Reset registered signals
      psel1_reg <= 0;
      psel2_reg <= 0;
      pwrite_reg <= 0;
      paddr_reg <= 9'b0;
      pwdata_reg <= 8'b0;
      read_reg <= 0;
      transfer_reg <= 0;
      apb_read_data_out <= 8'b0;
    end else begin
      state <= next_state;
      transfer_reg <= transfer;

      // Latch values during SETUP state
      if (state == SETUP) begin
        if (read && !write) begin
          paddr_reg  <= apb_read_paddr;
          psel1_reg  <= (apb_read_paddr[8] == 0);
          psel2_reg  <= (apb_read_paddr[8] == 1);
          pwrite_reg <= 0;
          read_reg   <= 1;
          pwdata_reg <= 8'b0;  // Clear write data during read
        end else if (write && !read) begin
          paddr_reg  <= apb_write_paddr;
          psel1_reg  <= (apb_write_paddr[8] == 0);
          psel2_reg  <= (apb_write_paddr[8] == 1);
          pwrite_reg <= 1;
          pwdata_reg <= apb_write_data;
          read_reg   <= 0;
        end else begin
          // Neither read nor write - clear all
          psel1_reg  <= 0;
          psel2_reg  <= 0;
          pwrite_reg <= 0;
          paddr_reg  <= 9'b0;
          pwdata_reg <= 8'b0;
          read_reg   <= 0;
        end
      end

      // Clear registered signals when transfer completes
      if ((state == ENABLE) && pready) begin
        // Transfer complete - clear select signals
        // This ensures PSEL is only active during the transfer
        if (!transfer) begin
          psel1_reg <= 0;
          psel2_reg <= 0;
        end
      end

      // Capture read data during ENABLE state when pready is high
      if (state == ENABLE && pready && read_reg) begin
        apb_read_data_out <= prdata;
      end
    end
  end
  // Combinational next state logic
  always @(*) begin
    case (state)
      IDLE: begin
        if (transfer) next_state = SETUP;
        else next_state = IDLE;
      end
      SETUP: begin
        next_state = ENABLE;  // Always move to ENABLE from SETUP
      end
      ENABLE: begin
        if (pready) next_state = (transfer) ? SETUP : IDLE;
        else next_state = ENABLE;
      end
      default: next_state = IDLE;
    endcase
  end
  // Output and state-dependent control logic
  always @(*) begin
    // Default assignments to prevent latches
    psel1   = 0;
    psel2   = 0;
    penable = 0;
    pwrite  = 0;
    paddr   = 9'b0;
    pwdata  = 8'b0;
    case (state)
      IDLE: begin
        // No activity in IDLE
      end
      SETUP: begin
        penable = 0;
        if (read && !write) begin
          paddr  = apb_read_paddr;
          psel1  = (apb_read_paddr[8] == 0);
          psel2  = (apb_read_paddr[8] == 1);
          pwrite = 0;
          pwdata = 8'b0;  // Clear data during read
        end else if (write && !read) begin
          paddr  = apb_write_paddr;
          psel1  = (apb_write_paddr[8] == 0);
          psel2  = (apb_write_paddr[8] == 1);
          pwrite = 1;
          pwdata = apb_write_data;
        end else begin
          // No operation
          psel1  = 0;
          psel2  = 0;
          pwrite = 0;
          paddr  = 9'b0;
          pwdata = 8'b0;
        end
      end
      ENABLE: begin
        penable = 1;
        // Use registered values to maintain signals
        psel1   = psel1_reg;
        psel2   = psel2_reg;
        pwrite  = pwrite_reg;
        paddr   = paddr_reg;
        pwdata  = pwdata_reg;
      end
    endcase
  end
endmodule

APB/apb_top.v


module apb_top (
    input  wire       pclk,              // Clock signal
    input  wire       presetn,           // Active-low reset
    input  wire       transfer,          // Signal to start transfer
    input  wire       read,              // Read control signal
    input  wire       write,             // Write control signal
    input  wire [8:0] apb_write_paddr,   // Write address from master
    input  wire [7:0] apb_write_data,    // Write data from master
    input  wire [8:0] apb_read_paddr,    // Read address from master
    output wire       pslverr,           // Slave error signal
    output wire [7:0] apb_read_data_out  // Data output during read
);

  // Internal wires to connect master and slaves
  wire       penable;  // Enable signal
  wire       pwrite;  // Write control signal
  wire [8:0] paddr;  // Address bus
  wire [7:0] pwdata;  // Write data bus
  wire [7:0] prdata1, prdata2;  // Read data from slaves
  wire pready1, pready2, pready;  // Ready signals
  wire psel1, psel2;  // Slave select signals

  // Master instance
  master master_inst (
      .presetn(presetn),
      .pclk(pclk),
      .transfer(transfer),
      .read(read),
      .write(write),
      .apb_write_paddr(apb_write_paddr),
      .apb_read_paddr(apb_read_paddr),
      .apb_write_data(apb_write_data),
      .pready(pready),
      .pslverr(pslverr),
      .prdata(prdata1),  // Combine read data buses (MUX internally based on psel)
      .psel1(psel1),
      .psel2(psel2),
      .penable(penable),
      .paddr(paddr),
      .pwrite(pwrite),
      .pwdata(pwdata),
      .apb_read_data_out(apb_read_data_out)
  );

  // Slave 1 instance
  slave slave1_inst (
      .pclk(pclk),
      .presetn(presetn),
      .psel(psel1),
      .penable(penable),
      .pwrite(pwrite),
      .paddr(paddr[7:0]),  // Addressing within slave 1 memory range
      .pwdata(pwdata),
      .prdata(prdata1),
      .pready(pready1),
      .pslverr(pslverr)
  );

  // Slave 2 instance
  slave slave2_inst (
      .pclk(pclk),
      .presetn(presetn),
      .psel(psel2),
      .penable(penable),
      .pwrite(pwrite),
      .paddr(paddr[7:0]),  // Addressing within slave 2 memory range
      .pwdata(pwdata),
      .prdata(prdata2),
      .pready(pready2),
      .pslverr(pslverr)
  );

  // Combine ready signals from slaves
  assign pready = (psel1 && pready1) || (psel2 && pready2);

endmodule

APB/tb_apb_top.v
`timescale 1ns / 1ps

module tb_apb_top;

  // Clock and reset signals
  reg pclk;
  reg presetn;

  // Master control signals
  reg transfer, read, write;
  reg [8:0] apb_write_paddr;
  reg [7:0] apb_write_data;
  reg [8:0] apb_read_paddr;

  // Outputs from the top module
  wire pslverr;
  wire [7:0] apb_read_data_out;

  // Clock generation (100 MHz)
  initial begin
    pclk = 0;
    forever #5 pclk = ~pclk;  
  end

  initial begin
    $dumpfile("tb_apb_top.vcd");
    $dumpvars(0, tb_apb_top);
  end

  // Instantiate the top module
  apb_top dut (
      .pclk(pclk),
      .presetn(presetn),
      .transfer(transfer),
      .read(read),
      .write(write),
      .apb_write_paddr(apb_write_paddr),
      .apb_write_data(apb_write_data),
      .apb_read_paddr(apb_read_paddr),
      .pslverr(pslverr),
      .apb_read_data_out(apb_read_data_out)
  );

  // Reset and Initialization
  task reset_and_init;
    begin
      presetn = 0;
      transfer = 0;
      read = 0;
      write = 0;
      apb_write_paddr = 9'b0;
      apb_write_data = 8'b0;
      apb_read_paddr = 9'b0;
      #20;  
      presetn = 1;
      #10;
    end
  endtask

  // Reusable Write Task (Cleaned output)
  task test_write;
    input [8:0] address;
    input [7:0] data;
    begin
      transfer = 1;
      write = 1;
      read = 0;
      apb_write_paddr = address;
      apb_write_data = data;
      #10;  // Setup phase
      #10;  // Access phase
      transfer = 0; 
      write = 0;
      $display("      [WRITE] Addr: %h | Data: %h", address, data);
      #10;
    end
  endtask

  // Reusable Read Task (Cleaned output and fixed timing)
  task test_read;
    input [8:0] address;
    begin
      transfer = 1;
      write = 0;
      read = 1;
      apb_read_paddr = address;
      #10;  // Setup phase
      #10;  // Access phase
      #1;   // Delay slightly to let the clock edge capture the data!
      $display("      [READ]  Addr: %h | Data Read: %h", address, apb_read_data_out);
      transfer = 0; 
      read = 0;
      #9;   // Balance the remaining 10ns window
    end
  endtask

  // Main Testbench Execution
  initial begin
    $display("\n=======================================================");
    $display("              APB SYSTEM TESTBENCH START               ");
    $display("=======================================================\n");
    
    reset_and_init;

    $display("\n---> [TC 1] Basic Write Operation");
    test_write(9'h005, 8'hAA);  

    $display("\n---> [TC 2] Basic Read Operation");
    test_read(9'h005);  

    $display("\n---> [TC 3] Address Decoding (Slave Selection)");
    $display("      Writing to Slave 1 (Addr 085) and Slave 2 (Addr 005)...");
    test_write(9'h085, 8'h5A);  
    test_write(9'h005, 8'hA5);  

    $display("\n---> [TC 4] Write with Wait States");
    // (Note: Slaves in this RTL do not support wait states, executes as normal write)
    test_write(9'h010, 8'hBB);  

    $display("\n---> [TC 5] Read with Wait States");
    test_read(9'h010);  

    $display("\n---> [TC 6] Error Handling (PSLVERR)");
    // To trigger an out-of-range error, we must write beyond the 8-bit limit.
    // However, since paddr inside the slave is [7:0], it physically cannot exceed 255.
    // We simulate the master sending a bad transaction.
    transfer = 1;
    write = 1;
    read = 0;
    apb_write_paddr = 9'h1FF;
    apb_write_data  = 8'hFF;
    #20;
    transfer = 0;
    write = 0;
    $display("      Error Condition PSLVERR = %b for Addr = 1FF", pslverr);
    #10;

    $display("\n---> [TC 7] Burst Transfers");
    test_write(9'h001, 8'h11);
    test_read(9'h001);
    test_write(9'h002, 8'h22);
    test_read(9'h002);
    test_write(9'h003, 8'h33);
    test_read(9'h003);

    $display("\n---> [TC 8] Out-of-Range Address");
    $display("      Testing hardware truncation physics (1FF truncates to FF)");
    transfer = 1; write = 1; read = 0;
    apb_write_paddr = 9'h1FF; apb_write_data = 8'hEE;
    #20; transfer = 0; write = 0;
    $display("      PSLVERR = %b (0 means hardware truncated and accepted it)", pslverr);
    #10;

    $display("\n---> [TC 9] Testing Reset Behavior");
    presetn = 0; 
    #20;
    if (!presetn) $display("      System Reset Asserted.");
    presetn = 1; 
    #10;
    if (presetn) $display("      System Reset Released. Registers reset.");
    #10;

    $display("\n---> [TC 10] Randomized Transactions");
    $display("      Executing 5 random transactions...");
    begin : random_block
      integer i;
      for (i = 0; i < 5; i = i + 1) begin
        if ($random % 2) begin
          test_write($random % 9'h100, $random % 8'hFF);
        end else begin
          test_read($random % 9'h100);
        end
      end
    end

    $display("\n=======================================================");
    $display("              APB SYSTEM TESTBENCH COMPLETE            ");
    $display("=======================================================\n");
    $finish;
  end

endmodule

APB/tb_apb_top.vcd
$date
	Mon Aug 17 01:51:54 2026
$end
$version
	Icarus Verilog
$end
$timescale
	1ps
$end
$scope module tb_apb_top $end
$var wire 1 ! pslverr $end
$var wire 8 " apb_read_data_out [7:0] $end
$var reg 9 # apb_read_paddr [8:0] $end
$var reg 8 $ apb_write_data [7:0] $end
$var reg 9 % apb_write_paddr [8:0] $end
$var reg 1 & pclk $end
$var reg 1 ' presetn $end
$var reg 1 ( read $end
$var reg 1 ) transfer $end
$var reg 1 * write $end
$scope module dut $end
$var wire 9 + apb_read_paddr [8:0] $end
$var wire 8 , apb_write_data [7:0] $end
$var wire 9 - apb_write_paddr [8:0] $end
$var wire 1 & pclk $end
$var wire 1 . pready $end
$var wire 1 ' presetn $end
$var wire 1 ! pslverr $end
$var wire 1 ( read $end
$var wire 1 ) transfer $end
$var wire 1 * write $end
$var wire 1 / pwrite $end
$var wire 8 0 pwdata [7:0] $end
$var wire 1 1 psel2 $end
$var wire 1 2 psel1 $end
$var wire 1 3 pready2 $end
$var wire 1 4 pready1 $end
$var wire 8 5 prdata2 [7:0] $end
$var wire 8 6 prdata1 [7:0] $end
$var wire 1 7 penable $end
$var wire 9 8 paddr [8:0] $end
$var wire 8 9 apb_read_data_out [7:0] $end
$scope module master_inst $end
$var wire 9 : apb_read_paddr [8:0] $end
$var wire 8 ; apb_write_data [7:0] $end
$var wire 9 < apb_write_paddr [8:0] $end
$var wire 1 & pclk $end
$var wire 1 . pready $end
$var wire 1 ' presetn $end
$var wire 1 ! pslverr $end
$var wire 1 ( read $end
$var wire 1 ) transfer $end
$var wire 1 * write $end
$var wire 8 = prdata [7:0] $end
$var parameter 2 > ENABLE $end
$var parameter 2 ? IDLE $end
$var parameter 2 @ SETUP $end
$var reg 8 A apb_read_data_out [7:0] $end
$var reg 2 B next_state [1:0] $end
$var reg 9 C paddr [8:0] $end
$var reg 9 D paddr_reg [8:0] $end
$var reg 1 7 penable $end
$var reg 1 2 psel1 $end
$var reg 1 E psel1_reg $end
$var reg 1 1 psel2 $end
$var reg 1 F psel2_reg $end
$var reg 8 G pwdata [7:0] $end
$var reg 8 H pwdata_reg [7:0] $end
$var reg 1 / pwrite $end
$var reg 1 I pwrite_reg $end
$var reg 1 J read_reg $end
$var reg 2 K state [1:0] $end
$var reg 1 L transfer_reg $end
$upscope $end
$scope module slave1_inst $end
$var wire 8 M paddr [7:0] $end
$var wire 1 & pclk $end
$var wire 1 7 penable $end
$var wire 1 ' presetn $end
$var wire 1 2 psel $end
$var wire 8 N pwdata [7:0] $end
$var wire 1 / pwrite $end
$var reg 8 O addr_reg [7:0] $end
$var reg 8 P prdata [7:0] $end
$var reg 1 4 pready $end
$var reg 1 Q pslverr $end
$upscope $end
$scope module slave2_inst $end
$var wire 8 R paddr [7:0] $end
$var wire 1 & pclk $end
$var wire 1 7 penable $end
$var wire 1 ' presetn $end
$var wire 1 1 psel $end
$var wire 8 S pwdata [7:0] $end
$var wire 1 / pwrite $end
$var reg 8 T addr_reg [7:0] $end
$var reg 8 U prdata [7:0] $end
$var reg 1 3 pready $end
$var reg 1 V pslverr $end
$upscope $end
$upscope $end
$scope begin random_block $end
$var integer 32 W i [31:0] $end
$upscope $end
$scope task reset_and_init $end
$upscope $end
$scope task test_read $end
$var reg 9 X address [8:0] $end
$upscope $end
$scope task test_write $end
$var reg 9 Y address [8:0] $end
$var reg 8 Z data [7:0] $end
$upscope $end
$upscope $end
$enddefinitions $end
$comment Show the parameter values. $end
$dumpall
b1 @
b0 ?
b10 >
$end
#0
$dumpvars
bx Z
bx Y
bx X
bx W
0V
bx U
b0 T
b0 S
b0 R
0Q
bx P
b0 O
b0 N
b0 M
0L
b0 K
0J
0I
b0 H
b0 G
0F
0E
b0 D
b0 C
b0 B
b0 A
bx =
b0 <
b0 ;
b0 :
b0 9
b0 8
07
bx 6
bx 5
04
03
02
01
b0 0
0/
0.
b0 -
b0 ,
b0 +
0*
0)
0(
0'
0&
b0 %
b0 $
b0 #
b0 "
0!
$end
#5000
1&
#10000
0&
#15000
1&
#20000
0&
1'
#25000
1&
#30000
b1 B
0&
b10101010 $
b10101010 ,
b10101010 ;
b101 %
b101 -
b101 <
1*
1)
b10101010 Z
b101 Y
#35000
b101 R
b101 M
b10101010 0
b10101010 G
b10101010 N
b10101010 S
1/
12
b101 8
b101 C
b10 B
1L
b1 K
1&
#40000
0&
#45000
17
b10101010 0
b10101010 G
b10101010 N
b10101010 S
b101 8
b101 C
1/
12
b10101010 H
1I
1E
b101 D
b10 K
1&
#50000
b10101010 0
b10101010 G
b10101010 N
b10101010 S
b101 8
b101 C
1/
17
12
0&
0*
0)
#55000
b0 B
1.
0L
14
1&
#60000
b10101010 0
b10101010 G
b10101010 N
b10101010 S
b101 8
b101 C
1/
17
12
b1 B
0&
b101 #
b101 +
b101 :
1(
1)
b101 X
#65000
b0 0
b0 G
b0 N
b0 S
b101 8
b101 C
0/
07
12
b10 B
14
1L
b1 K
1&
#70000
0&
#75000
0.
17
b101 8
b101 C
12
b10 B
b0 H
1J
0I
b10 K
04
1&
#80000
0&
#81000
b101 8
b101 C
17
12
0(
0)
#85000
b0 B
1.
14
b10101010 6
b10101010 =
b10101010 P
b101 O
0L
1&
#90000
b101 8
b101 C
17
12
b1 B
0&
b1011010 $
b1011010 ,
b1011010 ;
b10000101 %
b10000101 -
b10000101 <
1*
1)
b1011010 Z
b10000101 Y
#95000
b10000101 R
b10000101 M
b1011010 0
b1011010 G
b1011010 N
b1011010 S
1/
b10000101 8
b10000101 C
07
12
b10 B
b10101010 "
b10101010 9
b10101010 A
1L
b1 K
14
1&
#100000
0&
#105000
0.
17
b1011010 0
b1011010 G
b1011010 N
b1011010 S
b10000101 8
b10000101 C
1/
12
b10 B
04
0J
b1011010 H
1I
b10000101 D
b10 K
1&
#110000
b1011010 0
b1011010 G
b1011010 N
b1011010 S
b10000101 8
b10000101 C
1/
17
12
0&
0*
0)
#115000
b0 B
1.
0L
14
1&
#120000
b1011010 0
b1011010 G
b1011010 N
b1011010 S
b10000101 8
b10000101 C
1/
17
12
b1 B
0&
b10100101 $
b10100101 ,
b10100101 ;
b101 %
b101 -
b101 <
1*
1)
b10100101 Z
b101 Y
#125000
b101 R
b101 M
b10100101 0
b10100101 G
b10100101 N
b10100101 S
b101 8
b101 C
1/
07
12
b10 B
14
1L
b1 K
1&
#130000
0&
#135000
0.
17
b10100101 0
b10100101 G
b10100101 N
b10100101 S
b101 8
b101 C
1/
12
b10 B
b10100101 H
b101 D
b10 K
04
1&
#140000
b10100101 0
b10100101 G
b10100101 N
b10100101 S
b101 8
b101 C
1/
17
12
0&
0*
0)
#145000
b0 B
1.
14
0L
1&
#150000
b10100101 0
b10100101 G
b10100101 N
b10100101 S
b101 8
b101 C
1/
17
12
b1 B
0&
b10111011 $
b10111011 ,
b10111011 ;
b10000 %
b10000 -
b10000 <
1*
1)
b10111011 Z
b10000 Y
#155000
b10000 R
b10000 M
b10111011 0
b10111011 G
b10111011 N
b10111011 S
b10000 8
b10000 C
1/
07
12
b10 B
1L
b1 K
14
1&
#160000
0&
#165000
0.
17
b10111011 0
b10111011 G
b10111011 N
b10111011 S
b10000 8
b10000 C
1/
12
b10 B
04
b10111011 H
b10000 D
b10 K
1&
#170000
b10111011 0
b10111011 G
b10111011 N
b10111011 S
b10000 8
b10000 C
1/
17
12
0&
0*
0)
#175000
b0 B
1.
0L
14
1&
#180000
b10111011 0
b10111011 G
b10111011 N
b10111011 S
b10000 8
b10000 C
1/
17
12
b1 B
0&
b10000 #
b10000 +
b10000 :
1(
1)
b10000 X
#185000
b0 0
b0 G
b0 N
b0 S
b10000 8
b10000 C
0/
07
12
b10 B
14
1L
b1 K
1&
#190000
0&
#195000
0.
17
b10000 8
b10000 C
12
b10 B
b0 H
1J
0I
b10 K
04
1&
#200000
0&
#201000
b10000 8
b10000 C
17
12
0(
0)
#205000
b0 B
1.
14
b10111011 6
b10111011 =
b10111011 P
b10000 O
0L
1&
#210000
b10000 8
b10000 C
17
12
b1 B
0&
b11111111 $
b11111111 ,
b11111111 ;
b111111111 %
b111111111 -
b111111111 <
1*
1)
#215000
0.
b11111111 R
b11111111 M
b11111111 0
b11111111 G
b11111111 N
b11111111 S
1/
11
b111111111 8
b111111111 C
07
02
b10 B
b10111011 "
b10111011 9
b10111011 A
1L
b1 K
14
1&
#220000
0&
#225000
17
b11111111 0
b11111111 G
b11111111 N
b11111111 S
b111111111 8
b111111111 C
1/
11
04
0J
b11111111 H
1I
1F
0E
b111111111 D
b10 K
1&
#230000
b11111111 0
b11111111 G
b11111111 N
b11111111 S
b111111111 8
b111111111 C
1/
17
11
0&
0*
0)
#235000
b0 B
1.
0L
13
1&
#240000
b11111111 0
b11111111 G
b11111111 N
b11111111 S
b111111111 8
b111111111 C
1/
17
11
b1 B
0&
b10001 $
b10001 ,
b10001 ;
b1 %
b1 -
b1 <
1*
1)
b10001 Z
b1 Y
#245000
0.
b1 R
b1 M
12
b10001 0
b10001 G
b10001 N
b10001 S
b1 8
b1 C
1/
07
01
b10 B
13
1L
b1 K
1&
#250000
0&
#255000
17
b10001 0
b10001 G
b10001 N
b10001 S
b1 8
b1 C
1/
12
b10001 H
0F
1E
b1 D
b10 K
03
1&
#260000
b10001 0
b10001 G
b10001 N
b10001 S
b1 8
b1 C
1/
17
12
0&
0*
0)
#265000
b0 B
1.
14
0L
1&
#270000
b10001 0
b10001 G
b10001 N
b10001 S
b1 8
b1 C
1/
17
12
b1 B
0&
b1 #
b1 +
b1 :
1(
1)
b1 X
#275000
b0 0
b0 G
b0 N
b0 S
b1 8
b1 C
0/
07
12
b10 B
1L
b1 K
14
1&
#280000
0&
#285000
0.
17
b1 8
b1 C
12
b10 B
04
b0 H
1J
0I
b10 K
1&
#290000
0&
#291000
b1 8
b1 C
17
12
0(
0)
#295000
b0 B
1.
0L
14
b10001 6
b10001 =
b10001 P
b1 O
1&
#300000
b1 8
b1 C
17
12
b1 B
0&
b100010 $
b100010 ,
b100010 ;
b10 %
b10 -
b10 <
1*
1)
b100010 Z
b10 Y
#305000
b10 R
b10 M
b100010 0
b100010 G
b100010 N
b100010 S
1/
b10 8
b10 C
07
12
b10 B
14
b10001 "
b10001 9
b10001 A
1L
b1 K
1&
#310000
0&
#315000
0.
17
b100010 0
b100010 G
b100010 N
b100010 S
b10 8
b10 C
1/
12
b10 B
0J
b100010 H
1I
b10 D
b10 K
04
1&
#320000
b100010 0
b100010 G
b100010 N
b100010 S
b10 8
b10 C
1/
17
12
0&
0*
0)
#325000
b0 B
1.
14
0L
1&
#330000
b100010 0
b100010 G
b100010 N
b100010 S
b10 8
b10 C
1/
17
12
b1 B
0&
b10 #
b10 +
b10 :
1(
1)
b10 X
#335000
b0 0
b0 G
b0 N
b0 S
b10 8
b10 C
0/
07
12
b10 B
1L
b1 K
14
1&
#340000
0&
#345000
0.
17
b10 8
b10 C
12
b10 B
04
b0 H
1J
0I
b10 K
1&
#350000
0&
#351000
b10 8
b10 C
17
12
0(
0)
#355000
b0 B
1.
0L
14
b100010 6
b100010 =
b100010 P
b10 O
1&
#360000
b10 8
b10 C
17
12
b1 B
0&
b110011 $
b110011 ,
b110011 ;
b11 %
b11 -
b11 <
1*
1)
b110011 Z
b11 Y
#365000
b11 R
b11 M
b110011 0
b110011 G
b110011 N
b110011 S
1/
b11 8
b11 C
07
12
b10 B
14
b100010 "
b100010 9
b100010 A
1L
b1 K
1&
#370000
0&
#375000
0.
17
b110011 0
b110011 G
b110011 N
b110011 S
b11 8
b11 C
1/
12
b10 B
0J
b110011 H
1I
b11 D
b10 K
04
1&
#380000
b110011 0
b110011 G
b110011 N
b110011 S
b11 8
b11 C
1/
17
12
0&
0*
0)
#385000
b0 B
1.
14
0L
1&
#390000
b110011 0
b110011 G
b110011 N
b110011 S
b11 8
b11 C
1/
17
12
b1 B
0&
b11 #
b11 +
b11 :
1(
1)
b11 X
#395000
b0 0
b0 G
b0 N
b0 S
b11 8
b11 C
0/
07
12
b10 B
1L
b1 K
14
1&
#400000
0&
#405000
0.
17
b11 8
b11 C
12
b10 B
04
b0 H
1J
0I
b10 K
1&
#410000
0&
#411000
b11 8
b11 C
17
12
0(
0)
#415000
b0 B
1.
0L
14
b110011 6
b110011 =
b110011 P
b11 O
1&
#420000
b11 8
b11 C
17
12
b1 B
0&
b11101110 $
b11101110 ,
b11101110 ;
b111111111 %
b111111111 -
b111111111 <
1*
1)
#425000
0.
b11111111 R
b11111111 M
b11101110 0
b11101110 G
b11101110 N
b11101110 S
1/
11
b111111111 8
b111111111 C
07
02
b10 B
14
b110011 "
b110011 9
b110011 A
1L
b1 K
1&
#430000
0&
#435000
17
b11101110 0
b11101110 G
b11101110 N
b11101110 S
b111111111 8
b111111111 C
1/
11
0J
b11101110 H
1I
1F
0E
b111111111 D
b10 K
04
1&
#440000
b11101110 0
b11101110 G
b11101110 N
b11101110 S
b111111111 8
b111111111 C
1/
17
11
0&
0*
0)
#445000
b0 B
1.
13
0L
1&
#450000
b0 R
b0 M
0.
b0 0
b0 G
b0 N
b0 S
b0 8
b0 C
0/
07
01
b0 "
b0 9
b0 A
b0 H
b0 D
0I
0F
b0 K
b0 O
03
0&
0'
#455000
1&
#460000
0&
#465000
1&
#470000
0&
1'
#475000
1&
#480000
0&
#485000
1&
#490000
b1 B
0&
b10000001 #
b10000001 +
b10000001 :
1(
1)
b10000001 X
b0 W
#495000
b10000001 R
b10000001 M
12
b10000001 8
b10000001 C
b10 B
1L
b1 K
1&
#500000
0&
#505000
17
b10000001 8
b10000001 C
12
1J
1E
b10000001 D
b10 K
1&
#510000
0&
#511000
b10000001 8
b10000001 C
17
12
0(
0)
#515000
b0 B
1.
14
bx 6
bx =
bx P
b10000001 O
0L
1&
#520000
b10000001 8
b10000001 C
17
12
b1 B
0&
b1001000 $
b1001000 ,
b1001000 ;
b1100011 %
b1100011 -
b1100011 <
1*
1)
b1001000 Z
b1100011 Y
b1 W
#525000
b1100011 R
b1100011 M
b1001000 0
b1001000 G
b1001000 N
b1001000 S
1/
b1100011 8
b1100011 C
07
12
b10 B
bx "
bx 9
bx A
1L
b1 K
14
1&
#530000
0&
#535000
0.
17
b1001000 0
b1001000 G
b1001000 N
b1001000 S
b1100011 8
b1100011 C
1/
12
b10 B
04
0J
b1001000 H
1I
b1100011 D
b10 K
1&
#540000
b1001000 0
b1001000 G
b1001000 N
b1001000 S
b1100011 8
b1100011 C
1/
17
12
0&
0*
0)
#545000
b0 B
1.
0L
14
1&
#550000
b1001000 0
b1001000 G
b1001000 N
b1001000 S
b1100011 8
b1100011 C
1/
17
12
b1 B
0&
b100101 $
b100101 ,
b100101 ;
b1100101 %
b1100101 -
b1100101 <
1*
1)
b100101 Z
b1100101 Y
b10 W
#555000
b1100101 R
b1100101 M
b100101 0
b100101 G
b100101 N
b100101 S
b1100101 8
b1100101 C
1/
07
12
b10 B
14
1L
b1 K
1&
#560000
0&
#565000
0.
17
b100101 0
b100101 G
b100101 N
b100101 S
b1100101 8
b1100101 C
1/
12
b10 B
b100101 H
b1100101 D
b10 K
04
1&
#570000
b100101 0
b100101 G
b100101 N
b100101 S
b1100101 8
b1100101 C
1/
17
12
0&
0*
0)
#575000
b0 B
1.
14
0L
1&
#580000
b100101 0
b100101 G
b100101 N
b100101 S
b1100101 8
b1100101 C
1/
17
12
b1 B
0&
b11000110 $
b11000110 ,
b11000110 ;
b1101 %
b1101 -
b1101 <
1*
1)
b11000110 Z
b1101 Y
b11 W
#585000
b1101 R
b1101 M
b11000110 0
b11000110 G
b11000110 N
b11000110 S
b1101 8
b1101 C
1/
07
12
b10 B
1L
b1 K
14
1&
#590000
0&
#595000
0.
17
b11000110 0
b11000110 G
b11000110 N
b11000110 S
b1101 8
b1101 C
1/
12
b10 B
04
b11000110 H
b1101 D
b10 K
1&
#600000
b11000110 0
b11000110 G
b11000110 N
b11000110 S
b1101 8
b1101 C
1/
17
12
0&
0*
0)
#605000
b0 B
1.
0L
14
1&
#610000
b11000110 0
b11000110 G
b11000110 N
b11000110 S
b1101 8
b1101 C
1/
17
12
b1 B
0&
b11110111 $
b11110111 ,
b11110111 ;
b11101101 %
b11101101 -
b11101101 <
1*
1)
b11110111 Z
b11101101 Y
b100 W
#615000
b11101101 R
b11101101 M
b11110111 0
b11110111 G
b11110111 N
b11110111 S
b11101101 8
b11101101 C
1/
07
12
b10 B
14
1L
b1 K
1&
#620000
0&
#625000
0.
17
b11110111 0
b11110111 G
b11110111 N
b11110111 S
b11101101 8
b11101101 C
1/
12
b10 B
b11110111 H
b11101101 D
b10 K
04
1&
#630000
b11110111 0
b11110111 G
b11110111 N
b11110111 S
b11101101 8
b11101101 C
1/
17
12
0&
0*
0)
#635000
b0 B
1.
14
0L
1&
#640000
0&
b101 W
