AXI-LITE/axi_slave.v
module axi_slave #(
    parameter ADDRESS_WIDTH = 32,
    parameter DATA_WIDTH = 32
)(
    input  wire                     ACLK,
    input  wire                     ARESETN,

    input  wire [ADDRESS_WIDTH-1:0] ARADDR,
    input  wire                     ARVALID,
    output reg                      ARREADY,

    output reg  [DATA_WIDTH-1:0]    RDATA,
    output reg  [1:0]               RRESP,
    output reg                      RVALID,
    input  wire                     RREADY,

    input  wire [ADDRESS_WIDTH-1:0] AWADDR,
    input  wire                     AWVALID,
    output reg                      AWREADY,

    input  wire [DATA_WIDTH-1:0]    WDATA,
    input  wire [3:0]               WSTRB,
    input  wire                     WVALID,
    output reg                      WREADY,

    output reg  [1:0]               BRESP,
    output reg                      BVALID,
    input  wire                     BREADY
);

    reg [DATA_WIDTH-1:0] memory [0:255];
    
    reg [ADDRESS_WIDTH-1:0] read_addr_reg;
    reg [ADDRESS_WIDTH-1:0] write_addr_reg;

    always @(posedge ACLK or negedge ARESETN) begin
        if (!ARESETN) begin
            ARREADY <= 0; RVALID  <= 0; RDATA   <= 0; RRESP   <= 2'b00;
            AWREADY <= 0; WREADY  <= 0; BVALID  <= 0; BRESP   <= 2'b00;
        end else begin
            // Read Address Phase
            if (ARVALID && !ARREADY && !RVALID) begin
                ARREADY <= 1;
                read_addr_reg <= ARADDR;
            end else begin
                ARREADY <= 0;
            end

            // Read Data Phase
            if (ARREADY && ARVALID) begin
                RVALID <= 1;
                if (read_addr_reg < 256) begin
                    RDATA <= memory[read_addr_reg];
                    RRESP <= 2'b00; 
                end else begin
                    RDATA <= 0;
                    RRESP <= 2'b10; 
                end
            end else if (RVALID && RREADY) begin
                RVALID <= 0; 
            end

            // Write Address Phase
            if (AWVALID && !AWREADY && !BVALID) begin
                AWREADY <= 1;
                write_addr_reg <= AWADDR;
            end else begin
                AWREADY <= 0;
            end

            // Write Data Phase
            if (WVALID && !WREADY && !BVALID) begin
                WREADY <= 1;
            end else begin
                WREADY <= 0;
            end

            // Execute Write and Response
            if (AWREADY && AWVALID && WREADY && WVALID) begin
                if (write_addr_reg < 256) begin
                    memory[write_addr_reg] <= WDATA; 
                    BRESP <= 2'b00; 
                end else begin
                    BRESP <= 2'b10; 
                end
                BVALID <= 1;
            end else if (BVALID && BREADY) begin
                BVALID <= 0; 
            end
        end
    end
endmodule

AXI-LITE/axi_master.v
module axi_master #(
    parameter ADDRESS_WIDTH = 32,
    parameter DATA_WIDTH = 32
)(
    input  wire                     ACLK,
    input  wire                     ARESETN,
    
    input  wire                     START_READ,
    input  wire                     START_WRITE,
    input  wire [ADDRESS_WIDTH-1:0] address,
    input  wire [DATA_WIDTH-1:0]    W_data,

    output reg  [ADDRESS_WIDTH-1:0] ARADDR,
    output reg                      ARVALID,
    input  wire                     ARREADY,

    input  wire [DATA_WIDTH-1:0]    RDATA,
    input  wire [1:0]               RRESP,
    input  wire                     RVALID,
    output reg                      RREADY,

    output reg  [ADDRESS_WIDTH-1:0] AWADDR,
    output reg                      AWVALID,
    input  wire                     AWREADY,

    output reg  [DATA_WIDTH-1:0]    WDATA,
    output reg  [3:0]               WSTRB,
    output reg                      WVALID,
    input  wire                     WREADY,

    input  wire [1:0]               BRESP,
    input  wire                     BVALID,
    output reg                      BREADY
);

    localparam IDLE          = 3'b000;
    localparam RADDR_CHANNEL = 3'b001;
    localparam RDATA_CHANNEL = 3'b010;
    localparam WRITE_CHANNEL = 3'b011;
    localparam WRESP_CHANNEL = 3'b100;

    reg [2:0] state, next_state;

    always @(posedge ACLK or negedge ARESETN) begin
        if (!ARESETN) state <= IDLE;
        else state <= next_state;
    end

    // FSM State Transitions[cite: 4]
    always @(*) begin
        next_state = state; 
        case (state)
            IDLE: begin
                if (START_READ) next_state = RADDR_CHANNEL;
                else if (START_WRITE) next_state = WRITE_CHANNEL;
            end
            RADDR_CHANNEL: begin
                if (ARVALID && ARREADY) next_state = RDATA_CHANNEL;
            end
            RDATA_CHANNEL: begin
                if (RVALID && RREADY) next_state = IDLE;
            end
            WRITE_CHANNEL: begin
                if (AWVALID && AWREADY && WVALID && WREADY) next_state = WRESP_CHANNEL;
            end
            WRESP_CHANNEL: begin
                if (BVALID && BREADY) next_state = IDLE;
            end
            default: next_state = IDLE;
        endcase
    end

    always @(posedge ACLK or negedge ARESETN) begin
        if (!ARESETN) begin
            ARADDR  <= 0; ARVALID <= 0; RREADY  <= 0;
            AWADDR  <= 0; AWVALID <= 0; WDATA   <= 0;
            WSTRB   <= 4'b0000; WVALID  <= 0; BREADY  <= 0;
        end else begin
            // Default assignments to drop signals after handshakes
            ARVALID <= 0; RREADY  <= 0;
            AWVALID <= 0; WVALID  <= 0; BREADY  <= 0;

            case (next_state)
                IDLE: begin 
                end
                RADDR_CHANNEL: begin
                    ARADDR  <= address;
                    ARVALID <= 1; 
                end
                RDATA_CHANNEL: begin
                    RREADY <= 1; 
                end
                WRITE_CHANNEL: begin
                    AWADDR  <= address;
                    AWVALID <= 1;
                    WDATA   <= W_data;
                    WSTRB   <= 4'b1111; 
                    WVALID  <= 1;
                end
                WRESP_CHANNEL: begin
                    BREADY <= 1; 
                end
            endcase
        end
    end
endmodule

AXI-LITE/tb_axi_lite.v
`timescale 1ns / 1ps

module axi_tb();

    parameter ADDRESS_WIDTH = 32;
    parameter DATA_WIDTH = 32;

    reg ACLK;
    reg ARESETN;

    reg START_READ;
    reg START_WRITE;
    reg [ADDRESS_WIDTH-1:0] address;
    reg [DATA_WIDTH-1:0]    W_data;

    wire [ADDRESS_WIDTH-1:0] ARADDR;
    wire                     ARVALID;
    wire                     ARREADY;
    
    wire [DATA_WIDTH-1:0]    RDATA;
    wire [1:0]               RRESP;
    wire                     RVALID;
    wire                     RREADY;
    
    wire [ADDRESS_WIDTH-1:0] AWADDR;
    wire                     AWVALID;
    wire                     AWREADY;
    
    wire [DATA_WIDTH-1:0]    WDATA;
    wire [3:0]               WSTRB;
    wire                     WVALID;
    wire                     WREADY;
    
    wire [1:0]               BRESP;
    wire                     BVALID;
    wire                     BREADY;

    axi_master #(
        .ADDRESS_WIDTH(ADDRESS_WIDTH),
        .DATA_WIDTH(DATA_WIDTH)
    ) master_inst (
        .ACLK(ACLK),
        .ARESETN(ARESETN),
        .START_READ(START_READ),
        .START_WRITE(START_WRITE),
        .address(address),
        .W_data(W_data),
        
        .ARADDR(ARADDR), .ARVALID(ARVALID), .ARREADY(ARREADY),
        .RDATA(RDATA), .RRESP(RRESP), .RVALID(RVALID), .RREADY(RREADY),
        .AWADDR(AWADDR), .AWVALID(AWVALID), .AWREADY(AWREADY),
        .WDATA(WDATA), .WSTRB(WSTRB), .WVALID(WVALID), .WREADY(WREADY),
        .BRESP(BRESP), .BVALID(BVALID), .BREADY(BREADY)
    );

    axi_slave #(
        .ADDRESS_WIDTH(ADDRESS_WIDTH),
        .DATA_WIDTH(DATA_WIDTH)
    ) slave_inst (
        .ACLK(ACLK),
        .ARESETN(ARESETN),
        
        .ARADDR(ARADDR), .ARVALID(ARVALID), .ARREADY(ARREADY),
        .RDATA(RDATA), .RRESP(RRESP), .RVALID(RVALID), .RREADY(RREADY),
        .AWADDR(AWADDR), .AWVALID(AWVALID), .AWREADY(AWREADY),
        .WDATA(WDATA), .WSTRB(WSTRB), .WVALID(WVALID), .WREADY(WREADY),
        .BRESP(BRESP), .BVALID(BVALID), .BREADY(BREADY)
    );

    // Clock Generation (10ns period)
    initial ACLK = 0;
    always #5 ACLK = ~ACLK;

    // VCD Dump
    initial begin
        $dumpfile("axi_lite_waves.vcd");
        $dumpvars(0, axi_tb);
    end

    initial begin
        // Initialize Stimulus
        START_READ  = 0;
        START_WRITE = 0;
        address     = 0;
        W_data      = 0;
        
        // System Reset
        ARESETN = 0; #20;
        ARESETN = 1; #20;

        // TC1: Standard Write (OKAY)
        address     = 32'h00000010;
        W_data      = 32'hDEADBEEF;
        START_WRITE = 1; #10;
        START_WRITE = 0; 
        wait(BVALID && BREADY); #20; 

        // TC2: Standard Read (OKAY)
        address    = 32'h00000010;
        START_READ = 1; #10;
        START_READ = 0; 
        wait(RVALID && RREADY); #20; 

        // TC3: Out-of-Bounds Write (SLVERR)
        address     = 32'h00000200;
        W_data      = 32'hBAD0BAD0;
        START_WRITE = 1; #10;
        START_WRITE = 0;
        wait(BVALID && BREADY); #20;
        
        // TC4: Out-of-Bounds Read (SLVERR)
        address    = 32'h00000200;
        START_READ = 1; #10;
        START_READ = 0;
        wait(RVALID && RREADY); #40;

        $finish; 
    end

endmodule

AXI-LITE/axi_lite_waves.vcd
$date
	Mon Aug 24 01:55:13 2026
$end
$version
	Icarus Verilog
$end
$timescale
	1ps
$end
$scope module axi_tb $end
$var wire 1 ! WVALID $end
$var wire 4 " WSTRB [3:0] $end
$var wire 1 # WREADY $end
$var wire 32 $ WDATA [31:0] $end
$var wire 1 % RVALID $end
$var wire 2 & RRESP [1:0] $end
$var wire 1 ' RREADY $end
$var wire 32 ( RDATA [31:0] $end
$var wire 1 ) BVALID $end
$var wire 2 * BRESP [1:0] $end
$var wire 1 + BREADY $end
$var wire 1 , AWVALID $end
$var wire 1 - AWREADY $end
$var wire 32 . AWADDR [31:0] $end
$var wire 1 / ARVALID $end
$var wire 1 0 ARREADY $end
$var wire 32 1 ARADDR [31:0] $end
$var parameter 32 2 ADDRESS_WIDTH $end
$var parameter 32 3 DATA_WIDTH $end
$var reg 1 4 ACLK $end
$var reg 1 5 ARESETN $end
$var reg 1 6 START_READ $end
$var reg 1 7 START_WRITE $end
$var reg 32 8 W_data [31:0] $end
$var reg 32 9 address [31:0] $end
$scope module master_inst $end
$var wire 1 4 ACLK $end
$var wire 1 5 ARESETN $end
$var wire 1 6 START_READ $end
$var wire 1 7 START_WRITE $end
$var wire 32 : W_data [31:0] $end
$var wire 32 ; address [31:0] $end
$var wire 1 # WREADY $end
$var wire 1 % RVALID $end
$var wire 2 < RRESP [1:0] $end
$var wire 32 = RDATA [31:0] $end
$var wire 1 ) BVALID $end
$var wire 2 > BRESP [1:0] $end
$var wire 1 - AWREADY $end
$var wire 1 0 ARREADY $end
$var parameter 32 ? ADDRESS_WIDTH $end
$var parameter 32 @ DATA_WIDTH $end
$var parameter 3 A IDLE $end
$var parameter 3 B RADDR_CHANNEL $end
$var parameter 3 C RDATA_CHANNEL $end
$var parameter 3 D WRESP_CHANNEL $end
$var parameter 3 E WRITE_CHANNEL $end
$var reg 32 F ARADDR [31:0] $end
$var reg 1 / ARVALID $end
$var reg 32 G AWADDR [31:0] $end
$var reg 1 , AWVALID $end
$var reg 1 + BREADY $end
$var reg 1 ' RREADY $end
$var reg 32 H WDATA [31:0] $end
$var reg 4 I WSTRB [3:0] $end
$var reg 1 ! WVALID $end
$var reg 3 J next_state [2:0] $end
$var reg 3 K state [2:0] $end
$upscope $end
$scope module slave_inst $end
$var wire 1 4 ACLK $end
$var wire 32 L ARADDR [31:0] $end
$var wire 1 5 ARESETN $end
$var wire 1 / ARVALID $end
$var wire 32 M AWADDR [31:0] $end
$var wire 1 , AWVALID $end
$var wire 1 + BREADY $end
$var wire 1 ' RREADY $end
$var wire 32 N WDATA [31:0] $end
$var wire 4 O WSTRB [3:0] $end
$var wire 1 ! WVALID $end
$var parameter 32 P ADDRESS_WIDTH $end
$var parameter 32 Q DATA_WIDTH $end
$var reg 1 0 ARREADY $end
$var reg 1 - AWREADY $end
$var reg 2 R BRESP [1:0] $end
$var reg 1 ) BVALID $end
$var reg 32 S RDATA [31:0] $end
$var reg 2 T RRESP [1:0] $end
$var reg 1 % RVALID $end
$var reg 1 # WREADY $end
$var reg 32 U read_addr_reg [31:0] $end
$var reg 32 V write_addr_reg [31:0] $end
$upscope $end
$upscope $end
$enddefinitions $end
$comment Show the parameter values. $end
$dumpall
b100000 Q
b100000 P
b11 E
b100 D
b10 C
b1 B
b0 A
b100000 @
b100000 ?
b100000 3
b100000 2
$end
#0
$dumpvars
bx V
bx U
b0 T
b0 S
b0 R
b0 O
b0 N
b0 M
b0 L
b0 K
b0 J
b0 I
b0 H
b0 G
b0 F
b0 >
b0 =
b0 <
b0 ;
b0 :
b0 9
b0 8
07
06
05
04
b0 1
00
0/
b0 .
0-
0,
0+
b0 *
0)
b0 (
0'
b0 &
0%
b0 $
0#
b0 "
0!
$end
#5000
14
#10000
04
#15000
14
#20000
04
15
#25000
14
#30000
04
#35000
14
#40000
b11 J
04
17
b11011110101011011011111011101111 8
b11011110101011011011111011101111 :
b10000 9
b10000 ;
#45000
1!
b1111 "
b1111 I
b1111 O
b11011110101011011011111011101111 $
b11011110101011011011111011101111 H
b11011110101011011011111011101111 N
1,
b10000 .
b10000 G
b10000 M
b11 K
14
#50000
04
07
#55000
b100 J
1!
1,
1#
b10000 V
1-
14
#60000
04
#65000
b0 J
1)
0#
0-
1+
0!
0,
b100 K
14
#70000
04
#75000
b0 K
0+
0)
14
#80000
04
#85000
1/
b10000 1
b10000 F
b10000 L
b1 K
b1 J
14
16
#90000
04
#95000
b10 J
1/
b10000 U
10
14
06
#100000
04
#105000
b0 J
b11011110101011011011111011101111 (
b11011110101011011011111011101111 =
b11011110101011011011111011101111 S
1%
00
1'
0/
b10 K
14
#110000
04
#115000
b0 K
0'
0%
14
#120000
04
#125000
1!
b10111010110100001011101011010000 $
b10111010110100001011101011010000 H
b10111010110100001011101011010000 N
1,
b1000000000 .
b1000000000 G
b1000000000 M
b11 K
b11 J
14
17
b10111010110100001011101011010000 8
b10111010110100001011101011010000 :
b1000000000 9
b1000000000 ;
#130000
04
#135000
b100 J
1!
1,
1#
b1000000000 V
1-
14
07
#140000
04
#145000
b0 J
1)
b10 *
b10 >
b10 R
0#
0-
1+
0!
0,
b100 K
14
#150000
04
#155000
b0 K
0+
0)
14
#160000
04
#165000
1/
b1000000000 1
b1000000000 F
b1000000000 L
b1 K
b1 J
14
16
#170000
04
#175000
b10 J
1/
b1000000000 U
10
14
06
#180000
04
#185000
b0 J
b10 &
b10 <
b10 T
b0 (
b0 =
b0 S
1%
00
1'
0/
b10 K
14
#190000
04
#195000
b0 K
0'
0%
14
