AHB/AHB_MUX.v
// 2-cycle AHB error response for unmapped address regions
module AHB_MUX (
    input HCLK,
    input HRESETn,

    input        HRESP_Slave_1,
    input        HREADYOUT_1,
    input [31:0] HRDATA_Slave_1,

    input        HRESP_Slave_2,
    input        HREADYOUT_2,
    input [31:0] HRDATA_Slave_2,

    input [1:0] HSELx_Mux,

    output reg [31:0] HRDATA,
    output reg        HREADY,
    output reg        HRESP
);

    // err_phase drives the 2-cycle error response:
    //   err_phase=0 → HREADY=0, HRESP=1 (first  cycle)
    //   err_phase=1 → HREADY=1, HRESP=1 (second cycle)
    reg err_phase;

    always @(posedge HCLK or negedge HRESETn) begin
        if (!HRESETn)            err_phase <= 1'b0;
        else if (HSELx_Mux[1])  err_phase <= ~err_phase; // toggle through error cycles
        else                     err_phase <= 1'b0;
    end

    always @(*) begin
        case (HSELx_Mux)
            2'b00: begin
                HRDATA = HRDATA_Slave_1;
                HREADY = HREADYOUT_1;
                HRESP  = HRESP_Slave_1;
            end
            2'b01: begin
                HRDATA = HRDATA_Slave_2;
                HREADY = HREADYOUT_2;
                HRESP  = HRESP_Slave_2;
            end
            default: begin // unmapped region: AHB 2-cycle error response
                HRDATA = 32'h0;
                HRESP  = 1'b1;
                HREADY = err_phase;
            end
        endcase
    end

endmodule

AHB/AHB_Slave_2.v
module AHB_Slave_2 #(
    parameter MEM_WIDTH = 8,
    parameter MEM_DEPTH = 64
) (
    input HCLK,
    input HRESETn,

    input [31:0] HADDR,
    input [31:0] HWDATA,

    input [1:0] HSELx_slaves,

    input        HWRITE,
    input [2:0]  HSIZE,
    input [1:0]  HTRANS,
    input [2:0]  HBURST,
    input        HREADY,

    output reg        HREADYOUT,
    output reg        HRESP,
    output reg [31:0] HRDATA
);

    parameter IDLE  = 2'b00;
    parameter WRITE = 2'b01;
    parameter READ  = 2'b10;

    reg [1:0] curr_state, next_state;

    reg [MEM_WIDTH-1:0] memory_2[MEM_DEPTH-1:0];

    reg [31:0] HADDR_reg;
    reg        HWRITE_reg;
    reg [2:0]  HSIZE_reg;
    reg [1:0]  HTRANS_reg;
    reg [2:0]  HBURST_reg;

    reg [31:0] HADDR_Half;
    reg [31:0] HADDR_Full_1;
    reg [31:0] HADDR_Full_2;
    reg [31:0] HADDR_Full_3;

    reg ws_done; // tracks whether the 1-cycle wait-state has been served

    // FSM state register
    always @(posedge HCLK or negedge HRESETn) begin
        if (!HRESETn) curr_state <= IDLE;
        else          curr_state <= next_state;
    end

    // Next-state logic
    always @(*) begin
        next_state = curr_state;
        case (curr_state)
            IDLE: begin
                if (HREADY && HSELx_slaves == 2'b01 && (HTRANS == 2'b10 || HTRANS == 2'b11)) begin
                    if (HWRITE) next_state = WRITE;
                    else        next_state = READ;
                end
            end
            WRITE: begin
                if (!(HTRANS == 2'b10 || HTRANS == 2'b11)) next_state = IDLE;
                else if (!HWRITE)                           next_state = READ;
                else                                        next_state = WRITE;
            end
            READ: begin
                if (!(HTRANS == 2'b10 || HTRANS == 2'b11)) next_state = IDLE;
                else if (HWRITE)                            next_state = WRITE;
                else                                        next_state = READ;
            end
        endcase
    end

    // Output logic with 1-cycle wait-state insertion per transfer
    always @(posedge HCLK or negedge HRESETn) begin
        if (!HRESETn) begin
            HRDATA    <= 32'h0;
            HREADYOUT <= 1'b1;
            HRESP     <= 1'b0;
            ws_done   <= 1'b0;
        end else begin
            HRESP <= 1'b0;
            case (curr_state)
                READ: begin
                    if (!ws_done) begin
                        // First cycle in READ: drive HRDATA early, hold bus
                        HREADYOUT <= 1'b0;
                        ws_done   <= 1'b1;
                        if (HBURST == 3'b000 || HBURST == 3'b001) begin
                            case (HSIZE)
                                3'b000: HRDATA <= {24'h000000, memory_2[HADDR[29:0]]};
                                3'b001: HRDATA <= {16'h0000, memory_2[HADDR_Half], memory_2[HADDR[29:0]]};
                                3'b010: HRDATA <= {memory_2[HADDR_Full_3], memory_2[HADDR_Full_2],
                                                   memory_2[HADDR_Full_1], memory_2[HADDR[29:0]]};
                                default: HRDATA <= 32'h0;
                            endcase
                        end
                    end else begin
                        // Second cycle: release bus, HRDATA already valid
                        HREADYOUT <= 1'b1;
                        ws_done   <= 1'b0;
                    end
                end
                WRITE: begin
                    if (!ws_done) begin
                        // First cycle in WRITE: insert wait-state
                        HREADYOUT <= 1'b0;
                        ws_done   <= 1'b1;
                    end else begin
                        // Second cycle: perform write, release bus
                        HREADYOUT <= 1'b1;
                        ws_done   <= 1'b0;
                        if (HBURST_reg == 3'b000 || HBURST_reg == 3'b001) begin
                            case (HSIZE_reg)
                                3'b000: memory_2[HADDR_reg[29:0]] <= HWDATA[7:0];
                                3'b001: begin
                                    memory_2[HADDR_reg[29:0]] <= HWDATA[7:0];
                                    memory_2[HADDR_Half]      <= HWDATA[15:8];
                                end
                                3'b010: begin
                                    memory_2[HADDR_reg[29:0]] <= HWDATA[7:0];
                                    memory_2[HADDR_Full_1]    <= HWDATA[15:8];
                                    memory_2[HADDR_Full_2]    <= HWDATA[23:16];
                                    memory_2[HADDR_Full_3]    <= HWDATA[31:24];
                                end
                            endcase
                        end
                    end
                end
                default: begin
                    HREADYOUT <= 1'b1;
                    ws_done   <= 1'b0;
                end
            endcase
        end
    end

    // Address-phase capture register
    always @(posedge HCLK) begin
        if (HREADY && HSELx_slaves == 2'b01) begin
            HADDR_reg  <= HADDR;
            HWRITE_reg <= HWRITE;
            HSIZE_reg  <= HSIZE;
            HTRANS_reg <= HTRANS;
            HBURST_reg <= HBURST;
        end
    end

    // Sub-word address calculation
    always @(*) begin
        if (HREADY) begin
            if (HWRITE) begin
                HADDR_Half   = HADDR_reg[29:0] + 1;
                HADDR_Full_1 = HADDR_reg[29:0] + 1;
                HADDR_Full_2 = HADDR_reg[29:0] + 2;
                HADDR_Full_3 = HADDR_reg[29:0] + 3;
            end else begin
                HADDR_Half   = HADDR[29:0] + 1;
                HADDR_Full_1 = HADDR[29:0] + 1;
                HADDR_Full_2 = HADDR[29:0] + 2;
                HADDR_Full_3 = HADDR[29:0] + 3;
            end
        end else begin
            HADDR_Half   = HADDR_reg[29:0] + 1;
            HADDR_Full_1 = HADDR_reg[29:0] + 1;
            HADDR_Full_2 = HADDR_reg[29:0] + 2;
            HADDR_Full_3 = HADDR_reg[29:0] + 3;
        end
    end

endmodule

AHB/AHB_Slave_1.v
module AHB_Slave_1 #(
    parameter MEM_WIDTH = 8, 
    parameter MEM_DEPTH = 1024
) (
    input HCLK,
    input HRESETn,
    input [31:0] HADDR,
    input [31:0] HWDATA,
    input [1:0]  HSELx_slaves,
    input        HWRITE,
    input [2:0]  HSIZE,
    input [1:0]  HTRANS,
    input [2:0]  HBURST,
    input        HREADY,
    output reg        HREADYOUT,
    output reg        HRESP,
    output reg [31:0] HRDATA
);

    reg [MEM_WIDTH-1:0] memory [MEM_DEPTH-1:0];

    reg [31:0] HADDR_Half;
    reg [31:0] HADDR_Full_1;
    reg [31:0] HADDR_Full_2;
    reg [31:0] HADDR_Full_3;

    reg [31:0] HADDR_reg;
    reg        HWRITE_reg;
    reg [2:0]  HSIZE_reg;
    reg [1:0]  HTRANS_reg;
    reg [2:0]  HBURST_reg;

    always @(posedge HCLK or negedge HRESETn) begin
        if (!HRESETn) begin
            HREADYOUT <= 1'b1;
            HRESP     <= 1'b0;
            HRDATA    <= 32'h0;
        end else if (!HSELx_slaves && HREADY) begin
            if (HWRITE_reg && (HTRANS_reg == 2'b10 || HTRANS_reg == 2'b11)) begin
                if ((HBURST_reg == 3'b000 || HBURST_reg == 3'b001) && HSIZE_reg == 3'b000) begin 
                    memory[HADDR_reg[29:0]] <= HWDATA[7:0];
                end else if ((HBURST_reg == 3'b000 || HBURST_reg == 3'b001) && HSIZE_reg == 3'b001) begin
                    memory[HADDR_reg[29:0]] <= HWDATA[7:0];
                    memory[HADDR_Half]      <= HWDATA[15:8];
                end else if ((HBURST_reg == 3'b000 || HBURST_reg == 3'b001) && HSIZE_reg == 3'b010) begin
                    memory[HADDR_reg[29:0]] <= HWDATA[7:0];
                    memory[HADDR_Full_1]    <= HWDATA[15:8];
                    memory[HADDR_Full_2]    <= HWDATA[23:16];
                    memory[HADDR_Full_3]    <= HWDATA[31:24];
                end
            end else if (!HWRITE && (HTRANS == 2'b10 || HTRANS == 2'b11)) begin
                if ((HBURST == 3'b000 || HBURST == 3'b001) && HSIZE == 3'b000) begin 
                    HRDATA <= {24'h000000, memory[HADDR[29:0]]};
                end else if ((HBURST == 3'b000 || HBURST == 3'b001) && HSIZE == 3'b001) begin
                    HRDATA <= {16'h0000, memory[HADDR_Half], memory[HADDR[29:0]]};
                end else if ((HBURST == 3'b000 || HBURST == 3'b001) && HSIZE == 3'b010) begin
                    HRDATA <= {memory[HADDR_Full_3], memory[HADDR_Full_2], memory[HADDR_Full_1], memory[HADDR[29:0]]};
                end
            end
        end
    end

    always @(posedge HCLK) begin
        if (HREADY && HSELx_slaves == 2'b00) begin 
            HADDR_reg  <= HADDR;
            HWRITE_reg <= HWRITE;
            HSIZE_reg  <= HSIZE;
            HBURST_reg <= HBURST;
            HTRANS_reg <= HTRANS;
        end
    end

    always @(*) begin
        if (HREADY) begin
            if (HWRITE) begin
                HADDR_Half   = HADDR_reg[29:0] + 1;
                HADDR_Full_1 = HADDR_reg[29:0] + 1;
                HADDR_Full_2 = HADDR_reg[29:0] + 2;
                HADDR_Full_3 = HADDR_reg[29:0] + 3;
            end else begin
                HADDR_Half   = HADDR[29:0] + 1;
                HADDR_Full_1 = HADDR[29:0] + 1;
                HADDR_Full_2 = HADDR[29:0] + 2;
                HADDR_Full_3 = HADDR[29:0] + 3;
            end
        end else begin
            HADDR_Half   = HADDR_reg[29:0] + 1;
            HADDR_Full_1 = HADDR_reg[29:0] + 1;
            HADDR_Full_2 = HADDR_reg[29:0] + 2;
            HADDR_Full_3 = HADDR_reg[29:0] + 3;
        end
    end

endmodule

AHB/AHB_Decoder.v
module AHB_Decoder (
    input  [31:0] HADDR,
    output reg [1:0] HSELx_slaves,
    output reg [1:0] HSELx_Mux
);

    always @(*) begin
        case (HADDR[31:30])
            2'b00:   HSELx_slaves = 2'b00;
            2'b01:   HSELx_slaves = 2'b01;
            2'b10:   HSELx_slaves = 2'b10;
            2'b11:   HSELx_slaves = 2'b11;
            default: HSELx_slaves = 2'b00;
        endcase
        HSELx_Mux = HSELx_slaves;
    end

endmodule

AHB/AHB_Lite_Master.v
module AHB_Lite_Master (
    input  HCLK,
    input  HRESETn,
    // Processor-side inputs
    input  [31:0] PADDR,
    input  [31:0] PWDATA,
    input         PWRITE,
    input  [2:0]  PSIZE,
    input  [1:0]  PTRANS,
    input  [2:0]  PBURST,
    // AHB bus inputs
    input         HREADY,
    input         HRESP,
    input  [31:0] HRDATA,
    // AHB bus outputs
    output reg [31:0] HADDR,
    output reg [31:0] HWDATA,
    output reg        HWRITE,
    output reg [2:0]  HSIZE,
    output reg [1:0]  HTRANS,
    output reg [2:0]  HBURST,
    output reg        PDONE
);

    parameter IDLE   = 2'b00;
    parameter BUSY   = 2'b01;
    parameter NONSEQ = 2'b10;
    parameter SEQ    = 2'b11;

    reg [31:0] HWDATA_reg;
    reg [ 1:0] cs, ns;
    reg [ 1:0] beat_cnt; // counts beats for fixed-length bursts (INCR4)

    // State register
    always @(posedge HCLK or negedge HRESETn) begin
        if (!HRESETn) cs <= IDLE;
        else if (HREADY) cs <= ns;
    end

    // Next-state logic
    always @(*) begin
        case (cs)
            IDLE: begin
                if (PTRANS == 2'b10) ns = NONSEQ;
                else                  ns = IDLE;
            end
            BUSY: begin
                if      (PTRANS == 2'b11) ns = SEQ;
                else if (PTRANS == 2'b10) ns = NONSEQ;
                else if (PTRANS == 2'b00) ns = IDLE;
                else                      ns = BUSY;
            end
            NONSEQ: begin
                if      (PTRANS == 2'b11)                           ns = SEQ;
                else if (PTRANS == 2'b00)                           ns = IDLE;
                else if (PTRANS == 2'b10 && PBURST == 3'b000)       ns = NONSEQ;
                else                                                 ns = SEQ;
            end
            SEQ: begin
                // INCR4 (HBURST=011): auto-stop after 4 beats
                if      (PBURST == 3'b011 && beat_cnt == 2'd3)      ns = IDLE;
                else if (PTRANS == 2'b00)                           ns = IDLE;
                else if (PTRANS == 2'b10)                           ns = NONSEQ;
                else                                                 ns = SEQ;
            end
            default: ns = IDLE;
        endcase
    end

    // Output logic
    always @(posedge HCLK or negedge HRESETn) begin
        if (!HRESETn) begin
            HADDR      <= 32'b0;
            HWDATA_reg <= 32'b0;
            HWRITE     <= 1'b0;
            HSIZE      <= 3'b000;
            HTRANS     <= 2'b00;
            HBURST     <= 3'b000;
            beat_cnt   <= 2'd0;
        end else if (HREADY) begin
            case (cs)
                IDLE: begin
                    HADDR      <= 32'b0;
                    HWDATA_reg <= 32'b0;
                    HWRITE     <= 1'b0;
                    HSIZE      <= 3'b000;
                    HTRANS     <= 2'b00;
                    beat_cnt   <= 2'd0;
                end
                BUSY: begin
                    HADDR      <= PADDR;
                    HWDATA_reg <= PWDATA;
                    HWRITE     <= PWRITE;
                    HSIZE      <= PSIZE;
                    HTRANS     <= PTRANS;
                    HBURST     <= PBURST;
                end
                NONSEQ: begin
                    HADDR      <= PADDR;
                    HWDATA_reg <= PWDATA;
                    HWRITE     <= PWRITE;
                    HSIZE      <= PSIZE;
                    HTRANS     <= PTRANS;
                    HBURST     <= PBURST;
                    // Reset beat counter at start of fixed-length burst
                    beat_cnt   <= (PBURST == 3'b011) ? 2'd1 : 2'd0;
                end
                SEQ: begin
                    // INCR or INCR4: auto-increment address by transfer size
                    if ((PBURST == 3'b001 || PBURST == 3'b011) && PSIZE == 3'b000) begin
                        HADDR      <= HADDR + 1;
                        HWDATA_reg <= {24'h000000, PWDATA[7:0]};
                        HWRITE     <= PWRITE;
                        HSIZE      <= PSIZE;
                        HTRANS     <= 2'b11; // force SEQ on bus
                        HBURST     <= PBURST;
                    end else if ((PBURST == 3'b001 || PBURST == 3'b011) && PSIZE == 3'b001) begin
                        HADDR      <= HADDR + 2;
                        HWDATA_reg <= {16'h0000, PWDATA[15:0]};
                        HWRITE     <= PWRITE;
                        HSIZE      <= PSIZE;
                        HTRANS     <= 2'b11;
                        HBURST     <= PBURST;
                    end else if ((PBURST == 3'b001 || PBURST == 3'b011) && PSIZE == 3'b010) begin
                        HADDR      <= HADDR + 4;
                        HWDATA_reg <= PWDATA;
                        HWRITE     <= PWRITE;
                        HSIZE      <= PSIZE;
                        HTRANS     <= 2'b11;
                        HBURST     <= PBURST;
                    end else if (!PBURST) begin
                        HADDR      <= PADDR;
                        HWDATA_reg <= PWDATA;
                        HWRITE     <= PWRITE;
                        HSIZE      <= PSIZE;
                        HTRANS     <= PTRANS;
                        HBURST     <= PBURST;
                    end
                    // Advance beat counter for INCR4
                    if (PBURST == 3'b011) beat_cnt <= beat_cnt + 1;
                end
            endcase
        end
    end

    // Data phase: delay HWDATA by one cycle to respect AHB pipeline
    always @(posedge HCLK) begin
        if (HREADY) HWDATA <= HWDATA_reg;
    end

    // Transfer-done flag
    always @(*) begin
        if ((cs == NONSEQ || cs == SEQ) && ns == IDLE)
            PDONE = 1'b1;
        else
            PDONE = 1'b0;
    end

endmodule

AHB/AHB_TOP.v
`include "AHB_Lite_Master.v"
`include "AHB_Decoder.v"
`include "AHB_Slave_1.v"
`include "AHB_Slave_2.v"
`include "AHB_MUX.v"

module AHB_TOP (
    input        HCLK,
    input        HRESETn,
    // Processor-side interface
    input  [31:0] PADDR,
    input  [31:0] PWDATA,
    input         PWRITE,
    input  [2:0]  PSIZE,
    input  [1:0]  PTRANS,
    input  [2:0]  PBURST,
    output        PDONE
);

    wire [31:0] HADDR, HWDATA, HRDATA, HRDATA_1, HRDATA_2;
    wire        HWRITE, HREADY, HRESP, HRESP_Slave_1, HRESP_Slave_2;
    wire [2:0]  HSIZE, HBURST;
    wire [1:0]  HTRANS, HSELx_slaves, HSELx_Mux;
    wire        HREADYOUT_1, HREADYOUT_2;

    AHB_Lite_Master master (
        .HCLK(HCLK), .HRESETn(HRESETn),
        .PADDR(PADDR), .PWDATA(PWDATA), .PWRITE(PWRITE),
        .PSIZE(PSIZE), .PTRANS(PTRANS), .PBURST(PBURST),
        .HADDR(HADDR), .HWDATA(HWDATA), .HWRITE(HWRITE),
        .HSIZE(HSIZE), .HTRANS(HTRANS), .HBURST(HBURST),
        .HREADY(HREADY), .HRESP(HRESP), .HRDATA(HRDATA),
        .PDONE(PDONE)
    );

    AHB_Decoder decoder (
        .HADDR(HADDR),
        .HSELx_slaves(HSELx_slaves),
        .HSELx_Mux(HSELx_Mux)
    );

    AHB_Slave_1 slave1 (
        .HCLK(HCLK), .HRESETn(HRESETn),
        .HADDR(HADDR), .HWDATA(HWDATA),
        .HSELx_slaves(HSELx_slaves),
        .HWRITE(HWRITE), .HSIZE(HSIZE), .HTRANS(HTRANS),
        .HBURST(HBURST), .HREADY(HREADY),
        .HREADYOUT(HREADYOUT_1), .HRESP(HRESP_Slave_1), .HRDATA(HRDATA_1)
    );

    AHB_Slave_2 slave2 (
        .HCLK(HCLK), .HRESETn(HRESETn),
        .HADDR(HADDR), .HWDATA(HWDATA),
        .HSELx_slaves(HSELx_slaves),
        .HWRITE(HWRITE), .HSIZE(HSIZE), .HTRANS(HTRANS),
        .HBURST(HBURST), .HREADY(HREADY),
        .HREADYOUT(HREADYOUT_2), .HRESP(HRESP_Slave_2), .HRDATA(HRDATA_2)
    );

    AHB_MUX mux (
        .HCLK(HCLK), .HRESETn(HRESETn),
        .HRESP_Slave_1(HRESP_Slave_1), .HREADYOUT_1(HREADYOUT_1), .HRDATA_Slave_1(HRDATA_1),
        .HRESP_Slave_2(HRESP_Slave_2), .HREADYOUT_2(HREADYOUT_2), .HRDATA_Slave_2(HRDATA_2),
        .HSELx_Mux(HSELx_Mux),
        .HRDATA(HRDATA), .HREADY(HREADY), .HRESP(HRESP)
    );

endmodule

AHB/AHB_tb.v
`include "AHB_TOP.v"

module AHB_tb ();

    reg        HCLK, HRESETn;
    reg [31:0] PADDR, PWDATA;
    reg        PWRITE;
    reg [2:0]  PSIZE;
    reg [1:0]  PTRANS;
    reg [2:0]  PBURST;
    wire       PDONE;

    AHB_TOP top (
        .HCLK(HCLK), .HRESETn(HRESETn),
        .PADDR(PADDR), .PWDATA(PWDATA), .PWRITE(PWRITE),
        .PSIZE(PSIZE), .PTRANS(PTRANS), .PBURST(PBURST),
        .PDONE(PDONE)
    );

    initial HCLK = 0;
    always #10 HCLK = ~HCLK;

    // VCD Dump
    initial begin
        $dumpfile("ahb_waves.vcd");
        $dumpvars(0, AHB_tb);
    end

    // Utility task: single non-burst transfer
    task single_transfer;
        input [31:0] addr;
        input [31:0] wdata;
        input        write;
        input [2:0]  size;
        input        slave2;
        begin
            PADDR  = addr;
            PWDATA = wdata;
            PWRITE = write;
            PSIZE  = size;
            PTRANS = 2'b10;
            PBURST = 3'b000;
            if (slave2) #80;
            else        #40;
            PTRANS = 2'b00;
            #20;
        end
    endtask

    initial begin
        // Reset
        HRESETn = 0;
        PADDR   = 0; PWDATA = 0; PWRITE = 0;
        PSIZE   = 0; PTRANS = 0; PBURST = 0;
        #20;
        HRESETn = 1;
        #20;

        // TC1: Single Write
        single_transfer(32'h00000004, 32'hA5, 1, 3'b000, 0);
        single_transfer(32'h00000008, 32'hB6C7D8E9, 1, 3'b010, 0);
        PTRANS = 2'b00; #40;

        // TC2: Single Read
        single_transfer(32'h00000004, 0, 0, 3'b000, 0);
        single_transfer(32'h00000008, 0, 0, 3'b010, 0);
        PTRANS = 2'b00; #40;

        // TC3: Wait-state Write
        single_transfer(32'h40000004, 32'hAA, 1, 3'b000, 1);
        single_transfer(32'h40000010, 32'hA5B6, 1, 3'b001, 1);
        single_transfer(32'h40000020, 32'hDEADBEEF, 1, 3'b010, 1);
        single_transfer(32'h40000004, 0, 0, 3'b000, 1);
        single_transfer(32'h40000020, 0, 0, 3'b010, 1);
        PTRANS = 2'b00; #40;

        // TC4: INCR4 Burst
        PADDR  = 32'h00000100;
        PWDATA = 32'hAABBCCDD;
        PWRITE = 1;
        PSIZE  = 3'b010;
        PTRANS = 2'b10;
        PBURST = 3'b011;
        #20;
        PWDATA = 32'h11223344; #20;
        PWDATA = 32'h55667788; #20;
        PWDATA = 32'h99AABBCC; #20;
        PTRANS = 2'b00; #40;

        PADDR  = 32'h00000100;
        PWRITE = 0;
        PSIZE  = 3'b010;
        PTRANS = 2'b10;
        PBURST = 3'b011;
        #20;
        #20;
        #20;
        #20;
        PTRANS = 2'b00; #40;

        // TC5: Error Response
        PADDR  = 32'hC0000000;
        PWRITE = 0;
        PSIZE  = 3'b000;
        PTRANS = 2'b10;
        PBURST = 3'b000;
        #60;
        PTRANS = 2'b00;
        #40;

        $finish;
    end

endmodule

AHB/ahb_waves.vcd
$date
	Mon Aug 24 01:26:08 2026
$end
$version
	Icarus Verilog
$end
$timescale
	1s
$end
$scope module AHB_tb $end
$var wire 1 ! PDONE $end
$var reg 1 " HCLK $end
$var reg 1 # HRESETn $end
$var reg 32 $ PADDR [31:0] $end
$var reg 3 % PBURST [2:0] $end
$var reg 3 & PSIZE [2:0] $end
$var reg 2 ' PTRANS [1:0] $end
$var reg 32 ( PWDATA [31:0] $end
$var reg 1 ) PWRITE $end
$scope module top $end
$var wire 1 " HCLK $end
$var wire 1 # HRESETn $end
$var wire 32 * PADDR [31:0] $end
$var wire 3 + PBURST [2:0] $end
$var wire 3 , PSIZE [2:0] $end
$var wire 2 - PTRANS [1:0] $end
$var wire 32 . PWDATA [31:0] $end
$var wire 1 ) PWRITE $end
$var wire 1 ! PDONE $end
$var wire 1 / HWRITE $end
$var wire 32 0 HWDATA [31:0] $end
$var wire 2 1 HTRANS [1:0] $end
$var wire 3 2 HSIZE [2:0] $end
$var wire 2 3 HSELx_slaves [1:0] $end
$var wire 2 4 HSELx_Mux [1:0] $end
$var wire 1 5 HRESP_Slave_2 $end
$var wire 1 6 HRESP_Slave_1 $end
$var wire 1 7 HRESP $end
$var wire 1 8 HREADYOUT_2 $end
$var wire 1 9 HREADYOUT_1 $end
$var wire 1 : HREADY $end
$var wire 32 ; HRDATA_2 [31:0] $end
$var wire 32 < HRDATA_1 [31:0] $end
$var wire 32 = HRDATA [31:0] $end
$var wire 3 > HBURST [2:0] $end
$var wire 32 ? HADDR [31:0] $end
$scope module decoder $end
$var wire 32 @ HADDR [31:0] $end
$var reg 2 A HSELx_Mux [1:0] $end
$var reg 2 B HSELx_slaves [1:0] $end
$upscope $end
$scope module master $end
$var wire 1 " HCLK $end
$var wire 1 # HRESETn $end
$var wire 32 C PADDR [31:0] $end
$var wire 3 D PBURST [2:0] $end
$var wire 3 E PSIZE [2:0] $end
$var wire 2 F PTRANS [1:0] $end
$var wire 32 G PWDATA [31:0] $end
$var wire 1 ) PWRITE $end
$var wire 1 7 HRESP $end
$var wire 1 : HREADY $end
$var wire 32 H HRDATA [31:0] $end
$var parameter 2 I BUSY $end
$var parameter 2 J IDLE $end
$var parameter 2 K NONSEQ $end
$var parameter 2 L SEQ $end
$var reg 32 M HADDR [31:0] $end
$var reg 3 N HBURST [2:0] $end
$var reg 3 O HSIZE [2:0] $end
$var reg 2 P HTRANS [1:0] $end
$var reg 32 Q HWDATA [31:0] $end
$var reg 32 R HWDATA_reg [31:0] $end
$var reg 1 / HWRITE $end
$var reg 1 ! PDONE $end
$var reg 2 S beat_cnt [1:0] $end
$var reg 2 T cs [1:0] $end
$var reg 2 U ns [1:0] $end
$upscope $end
$scope module mux $end
$var wire 1 " HCLK $end
$var wire 1 # HRESETn $end
$var wire 2 V HSELx_Mux [1:0] $end
$var wire 1 5 HRESP_Slave_2 $end
$var wire 1 6 HRESP_Slave_1 $end
$var wire 1 8 HREADYOUT_2 $end
$var wire 1 9 HREADYOUT_1 $end
$var wire 32 W HRDATA_Slave_2 [31:0] $end
$var wire 32 X HRDATA_Slave_1 [31:0] $end
$var reg 32 Y HRDATA [31:0] $end
$var reg 1 : HREADY $end
$var reg 1 7 HRESP $end
$var reg 1 Z err_phase $end
$upscope $end
$scope module slave1 $end
$var wire 32 [ HADDR [31:0] $end
$var wire 3 \ HBURST [2:0] $end
$var wire 1 " HCLK $end
$var wire 1 : HREADY $end
$var wire 1 # HRESETn $end
$var wire 2 ] HSELx_slaves [1:0] $end
$var wire 3 ^ HSIZE [2:0] $end
$var wire 2 _ HTRANS [1:0] $end
$var wire 32 ` HWDATA [31:0] $end
$var wire 1 / HWRITE $end
$var parameter 32 a MEM_DEPTH $end
$var parameter 32 b MEM_WIDTH $end
$var reg 32 c HADDR_Full_1 [31:0] $end
$var reg 32 d HADDR_Full_2 [31:0] $end
$var reg 32 e HADDR_Full_3 [31:0] $end
$var reg 32 f HADDR_Half [31:0] $end
$var reg 32 g HADDR_reg [31:0] $end
$var reg 3 h HBURST_reg [2:0] $end
$var reg 32 i HRDATA [31:0] $end
$var reg 1 9 HREADYOUT $end
$var reg 1 6 HRESP $end
$var reg 3 j HSIZE_reg [2:0] $end
$var reg 2 k HTRANS_reg [1:0] $end
$var reg 1 l HWRITE_reg $end
$upscope $end
$scope module slave2 $end
$var wire 32 m HADDR [31:0] $end
$var wire 3 n HBURST [2:0] $end
$var wire 1 " HCLK $end
$var wire 1 : HREADY $end
$var wire 1 # HRESETn $end
$var wire 2 o HSELx_slaves [1:0] $end
$var wire 3 p HSIZE [2:0] $end
$var wire 2 q HTRANS [1:0] $end
$var wire 32 r HWDATA [31:0] $end
$var wire 1 / HWRITE $end
$var parameter 2 s IDLE $end
$var parameter 32 t MEM_DEPTH $end
$var parameter 32 u MEM_WIDTH $end
$var parameter 2 v READ $end
$var parameter 2 w WRITE $end
$var reg 32 x HADDR_Full_1 [31:0] $end
$var reg 32 y HADDR_Full_2 [31:0] $end
$var reg 32 z HADDR_Full_3 [31:0] $end
$var reg 32 { HADDR_Half [31:0] $end
$var reg 32 | HADDR_reg [31:0] $end
$var reg 3 } HBURST_reg [2:0] $end
$var reg 32 ~ HRDATA [31:0] $end
$var reg 1 8 HREADYOUT $end
$var reg 1 5 HRESP $end
$var reg 3 !" HSIZE_reg [2:0] $end
$var reg 2 "" HTRANS_reg [1:0] $end
$var reg 1 #" HWRITE_reg $end
$var reg 2 $" curr_state [1:0] $end
$var reg 2 %" next_state [1:0] $end
$var reg 1 &" ws_done $end
$upscope $end
$upscope $end
$scope task single_transfer $end
$var reg 32 '" addr [31:0] $end
$var reg 3 (" size [2:0] $end
$var reg 1 )" slave2 $end
$var reg 32 *" wdata [31:0] $end
$var reg 1 +" write $end
$upscope $end
$upscope $end
$enddefinitions $end
$comment Show the parameter values. $end
$dumpall
b1 w
b10 v
b1000 u
b1000000 t
b0 s
b1000 b
b10000000000 a
b11 L
b10 K
b0 J
b1 I
$end
#0
$dumpvars
x+"
bx *"
x)"
bx ("
bx '"
0&"
b0 %"
b0 $"
x#"
bx ""
bx !"
b0 ~
bx }
bx |
b1 {
b11 z
b10 y
b1 x
bx r
b0 q
b0 p
b0 o
b0 n
b0 m
xl
bx k
bx j
b0 i
bx h
bx g
b1 f
b11 e
b10 d
b1 c
bx `
b0 _
b0 ^
b0 ]
b0 \
b0 [
0Z
b0 Y
b0 X
b0 W
b0 V
b0 U
b0 T
b0 S
b0 R
bx Q
b0 P
b0 O
b0 N
b0 M
b0 H
b0 G
b0 F
b0 E
b0 D
b0 C
b0 B
b0 A
b0 @
b0 ?
b0 >
b0 =
b0 <
b0 ;
1:
19
18
07
06
05
b0 4
b0 3
b0 2
b0 1
bx 0
0/
b0 .
b0 -
b0 ,
b0 +
b0 *
0)
b0 (
b0 '
b0 &
b0 %
b0 $
0#
0"
0!
$end
#10
b0 0
b0 Q
b0 `
b0 r
b0 k
b0 h
b0 j
0l
b0 g
1"
#20
0"
1#
#30
1"
#40
b10 U
0"
b10 '
b10 -
b10 F
1)
b10100101 (
b10100101 .
b10100101 G
b100 $
b100 *
b100 C
0)"
b0 ("
1+"
b10100101 *"
b100 '"
#50
b10 T
1"
#60
0"
#70
bx z
bx y
bx x
bx {
b10 1
b10 P
b10 _
b10 q
1/
b10100101 R
b100 ?
b100 @
b100 M
b100 [
b100 m
1"
#80
1!
b0 U
0"
b0 '
b0 -
b0 F
#90
b111 e
b110 d
b101 c
b101 f
0!
b10100101 0
b10100101 Q
b10100101 `
b10100101 r
b10 k
1l
b100 g
b0 1
b0 P
b0 _
b0 q
b0 T
1"
#100
b10 U
0"
b10 '
b10 -
b10 F
b10 &
b10 ,
b10 E
b10110110110001111101100011101001 (
b10110110110001111101100011101001 .
b10110110110001111101100011101001 G
b1000 $
b1000 *
b1000 C
b10 ("
b10110110110001111101100011101001 *"
b1000 '"
#110
b11 e
b10 d
b1 c
b1 f
b11 z
b10 y
b1 x
b1 {
b0 k
b10 T
0/
b0 R
b0 ?
b0 @
b0 M
b0 [
b0 m
1"
#120
0"
#130
bx z
bx y
bx x
bx {
b0 0
b0 Q
b0 `
b0 r
0l
b0 g
b10 1
b10 P
b10 _
b10 q
b10 2
b10 O
b10 ^
b10 p
1/
b10110110110001111101100011101001 R
b1000 ?
b1000 @
b1000 M
b1000 [
b1000 m
1"
#140
1!
b0 U
0"
b0 '
b0 -
b0 F
#150
b1011 e
b1010 d
b1001 c
b1001 f
0!
b10 k
b10 j
1l
b1000 g
b10110110110001111101100011101001 0
b10110110110001111101100011101001 Q
b10110110110001111101100011101001 `
b10110110110001111101100011101001 r
b0 T
b0 1
b0 P
b0 _
b0 q
1"
#160
0"
#170
b11 e
b10 d
b1 c
b1 f
b11 z
b10 y
b1 x
b1 {
b0 k
b0 2
b0 O
b0 ^
b0 p
0/
b0 R
b0 ?
b0 @
b0 M
b0 [
b0 m
1"
#180
0"
